{
  "meta": {
    "state": "SC",
    "level": "local",
    "jurisdiction": "county:dorchester",
    "label": "Dorchester County Council",
    "lastUpdated": "2026-04-06",
    "adapter": "scac",
    "dataHash": "1397ae5b51e060ab",
    "dataLastChanged": "2026-04-06"
  },
  "members": [
    {
      "name": "C. David Chinnis",
      "title": "Chairman",
      "email": "",
      "phone": "(843) 801-2326",
      "source": "scac",
      "lastUpdated": "2026-04-06"
    },
    {
      "name": "Rita May Ranck",
      "title": "Vice Chairman",
      "email": "",
      "phone": "(843) 955-9708",
      "source": "scac",
      "lastUpdated": "2026-04-06"
    },
    {
      "name": "DorchesterCouncil Vacant",
      "title": "Council Member",
      "email": "",
      "phone": "(843) 563-0100",
      "source": "scac",
      "lastUpdated": "2026-04-06"
    },
    {
      "name": "Edward Crosby",
      "title": "Council Member",
      "email": "",
      "phone": "(843) 832-0196",
      "source": "scac",
      "lastUpdated": "2026-04-06"
    },
    {
      "name": "James Byars",
      "title": "Council Member",
      "email": "",
      "phone": "(843) 832-0196",
      "source": "scac",
      "lastUpdated": "2026-04-06"
    },
    {
      "name": "Peter Smith",
      "title": "Council Member",
      "email": "",
      "phone": "(843) 853-1174",
      "source": "scac",
      "lastUpdated": "2026-04-06"
    },
    {
      "name": "S. Todd Friddle",
      "title": "Council Member",
      "email": "",
      "phone": "(843) 805-2258",
      "source": "scac",
      "lastUpdated": "2026-04-06"
    }
  ]
}
