{
  "meta": {
    "state": "SC",
    "level": "local",
    "jurisdiction": "county:greenwood",
    "label": "Greenwood County Council",
    "lastUpdated": "2026-03-13",
    "adapter": "manual"
  },
  "members": [
    {
      "name": "Teresa Griffin",
      "title": "Council Member, District 1",
      "email": "",
      "phone": "",
      "source": "manual",
      "lastUpdated": "2026-03-04"
    },
    {
      "name": "Mark Allison",
      "title": "Council Member, District 2",
      "email": "",
      "phone": "",
      "source": "manual",
      "lastUpdated": "2026-03-04"
    },
    {
      "name": "Johanna Bishop",
      "title": "Council Member, District 3",
      "email": "",
      "phone": "",
      "source": "manual",
      "lastUpdated": "2026-03-04"
    },
    {
      "name": "Cathy Miller",
      "title": "Council Member, District 4",
      "email": "",
      "phone": "",
      "source": "manual",
      "lastUpdated": "2026-03-04"
    },
    {
      "name": "Dayne Pruitt",
      "title": "Vice Chairman, District 5",
      "email": "",
      "phone": "",
      "source": "manual",
      "lastUpdated": "2026-03-04"
    },
    {
      "name": "Robbie Templeton",
      "title": "Council Member, District 6",
      "email": "",
      "phone": "",
      "source": "manual",
      "lastUpdated": "2026-03-04"
    },
    {
      "name": "Theo Lane",
      "title": "Chairman, District 7",
      "email": "",
      "phone": "",
      "source": "manual",
      "lastUpdated": "2026-03-04"
    }
  ]
}
