{
  "meta": {
    "state": "SC",
    "level": "local",
    "jurisdiction": "place:gaffney",
    "label": "Gaffney City Council",
    "lastUpdated": "2026-06-09",
    "adapter": "gaffney_city",
    "dataHash": "7c711cf677444b01",
    "dataLastChanged": "2026-06-09"
  },
  "members": [
    {
      "name": "Lyman D. Dawkins III",
      "title": "Mayor",
      "email": "Ldawkins@cityofgaffney-sc.gov",
      "phone": "",
      "source": "gaffneycity",
      "lastUpdated": "2026-06-09",
      "vacant": false,
      "office": "mayor",
      "leadership": null,
      "seatClass": "at-large",
      "seatLabel": null,
      "seatId": null,
      "seatSource": "parsed-title",
      "partisan": false
    },
    {
      "name": "Cameo Wilson",
      "title": "Council Member, District 1",
      "email": "CWilson@cityofgaffney-sc.gov",
      "phone": "",
      "source": "gaffneycity",
      "lastUpdated": "2026-06-09",
      "vacant": false,
      "office": "council-member",
      "seatClass": "numbered",
      "seatLabel": "district",
      "seatId": "1",
      "seatSource": "parsed-title",
      "leadership": null,
      "partisan": false
    },
    {
      "name": "C. Allen Montgomery, Jr",
      "title": "Council Member, District 2",
      "email": "amontgomery@cityofgaffney-sc.gov",
      "phone": "",
      "source": "gaffneycity",
      "lastUpdated": "2026-06-09",
      "vacant": false,
      "office": "council-member",
      "seatClass": "numbered",
      "seatLabel": "district",
      "seatId": "2",
      "seatSource": "parsed-title",
      "leadership": null,
      "partisan": false
    },
    {
      "name": "Rosa Webber",
      "title": "Council Member, District 3",
      "email": "rwebber@cityofgaffney-sc.gov",
      "phone": "",
      "source": "gaffneycity",
      "lastUpdated": "2026-06-09",
      "vacant": false,
      "office": "council-member",
      "seatClass": "numbered",
      "seatLabel": "district",
      "seatId": "3",
      "seatSource": "parsed-title",
      "leadership": null,
      "partisan": false
    },
    {
      "name": "George Duncan",
      "title": "Council Member, District 4",
      "email": "Gduncan@cityofgaffney-sc.gov",
      "phone": "",
      "source": "gaffneycity",
      "lastUpdated": "2026-06-09",
      "vacant": false,
      "office": "council-member",
      "seatClass": "numbered",
      "seatLabel": "district",
      "seatId": "4",
      "seatSource": "parsed-title",
      "leadership": null,
      "partisan": false
    },
    {
      "name": "Kim F. Phillips",
      "title": "Council Member, District 5",
      "email": "kfphillips59@gmail.com",
      "phone": "",
      "source": "gaffneycity",
      "lastUpdated": "2026-06-09",
      "vacant": false,
      "office": "council-member",
      "seatClass": "numbered",
      "seatLabel": "district",
      "seatId": "5",
      "seatSource": "parsed-title",
      "leadership": null,
      "partisan": false
    },
    {
      "name": "Quay Little",
      "title": "Council Member, District 6",
      "email": "qlittle@cityofgaffney-sc.gov",
      "phone": "",
      "source": "gaffneycity",
      "lastUpdated": "2026-06-09",
      "vacant": false,
      "office": "council-member",
      "seatClass": "numbered",
      "seatLabel": "district",
      "seatId": "6",
      "seatSource": "parsed-title",
      "leadership": null,
      "partisan": false
    }
  ]
}
